data_engineering_extract_metadata/README.md
data_engineering_extract_metadata/__init__.py
data_engineering_extract_metadata/connect.py
data_engineering_extract_metadata/metadata.py
data_engineering_extract_metadata/utils.py
data_engineering_extract_metadata-2.0.0.dist-info/WHEEL
data_engineering_extract_metadata-2.0.0.dist-info/METADATA
data_engineering_extract_metadata-2.0.0.dist-info/RECORD
