Metadata-Version: 2.1
Name: data-engineering-extract-metadata
Version: 2.0.0
Summary: A python package for extracting and formatting table metadata from databases
Home-page: https://github.com/moj-analytical-services/data-engineering-extract-metadata
License: MIT
Author: Alec Johnson
Author-email: alec.johnson@digital.justice.gov.uk
Requires-Python: >=3.6,<4.0
Classifier: License :: OSI Approved :: MIT License
Classifier: Programming Language :: Python :: 3
Classifier: Programming Language :: Python :: 3.6
Classifier: Programming Language :: Python :: 3.7
Classifier: Programming Language :: Python :: 3.8
Classifier: Programming Language :: Python :: 3.9
Requires-Dist: cx_Oracle (>=8.0.0,<9.0.0)
Project-URL: Repository, https://github.com/moj-analytical-services/data-engineering-extract-metadata
